Workbook
Name aporte: 'Evidência Agressivo'!$D$10
Name aporte: 'Evidência Conservador'!$D$10
Name aporte: APP!$D$10
Name patrimonio: 'Evidência Agressivo'!$D$13
Name patrimonio: 'Evidência Conservador'!$D$13
Name patrimonio: APP!$D$13
Name qtd_anos: 'Evidência Agressivo'!$D$11
Name qtd_anos: 'Evidência Conservador'!$D$11
Name qtd_anos: APP!$D$11
Name rendimento_carteira: 'Evidência Agressivo'!$D$6
Name rendimento_carteira: 'Evidência Conservador'!$D$6
Name rendimento_carteira: APP!$D$6
Name taxa_mensal: 'Evidência Agressivo'!$D$12
Name taxa_mensal: 'Evidência Conservador'!$D$12
Name taxa_mensal: APP!$D$12

Sheet APP
B2: RHAVENA SÁ - INVESTIMENTOS
B4: CONFIGURAÇÕES
B5: Salário | D5: 15000
B6: Rendimento Carteira | D6: 0.006
B7: Sugestão de Investimento (30%) | D7: =D5*30% -> 4500
B9: INVESTIMENTO MENSAL
B10: Quanto investir por mês ? | D10: 1000
B11: Por Quantos Anos ? | D11: 10
B12: Taxa de Rendimento mensal ? | D12: 0.01079
B13: Patrimônio acumulado ? | D13: =FV(taxa_mensal,qtd_anos*12,aporte*-1) -> 243284.21
B14: Dividendos Mensais ? | D14: =patrimonio*rendimento_carteira -> 1459.7053
B16: Cenários | D16: Dividendo
A17: 2 | B17: Quanto em 2 Anos ? | C17: =FV($D$12,$A17*12,$D$10*-1) -> 27227.627 | D17: =C17*rendimento_carteira -> 163.36576
A18: 5 | B18: Quanto em 5 Anos ? | C18: =FV($D$12,$A18*12,$D$10*-1) -> 83776.914 | D18: =C18*rendimento_carteira -> 502.66148
A19: 10 | B19: Quanto em 10 Anos ? | C19: =FV($D$12,$A19*12,$D$10*-1) -> 243284.21 | D19: =C19*rendimento_carteira -> 1459.7053
A20: 20 | B20: Quanto em 20 Anos ? | C20: =FV($D$12,$A20*12,$D$10*-1) -> 1125198.4 | D20: =C20*rendimento_carteira -> 6751.1904
A21: 30 | B21: Quanto em 30 Anos ? | C21: =FV($D$12,$A21*12,$D$10*-1) -> 4322169.7 | D21: =C21*rendimento_carteira -> 25933.018
B25: PERFIL | C25: Conservador
B26: VALOR A SER INVESTIDO POR MÊS | C26: =aporte -> 1000
B28: TIPO DE FII | C28: Percentual Sugerido | D28: Valores
B29: PAPEL | C29: =VLOOKUP($C$25&"-"&B29,Sheet2!$A:$D,4,FALSE) -> 0.3 | D29: =C29*$C$26 -> 300
B30: TIJOLO | C30: =VLOOKUP($C$25&"-"&B30,Sheet2!$A:$D,4,FALSE) -> 0.5 | D30: =C30*$C$26 -> 500
B31: HÍBRIDOS | C31: =VLOOKUP($C$25&"-"&B31,Sheet2!$A:$D,4,FALSE) -> 0.1 | D31: =C31*$C$26 -> 100
B32: FOFs | C32: =VLOOKUP($C$25&"-"&B32,Sheet2!$A:$D,4,FALSE) -> 0.1 | D32: =C32*$C$26 -> 100
B33: DESENVOLVIMENTO | C33: =VLOOKUP($C$25&"-"&B33,Sheet2!$A:$D,4,FALSE) -> 0 | D33: =C33*$C$26 -> 0
B34: HOTELARIAS | C34: =VLOOKUP($C$25&"-"&B34,Sheet2!$A:$D,4,FALSE) -> 0 | D34: =C34*$C$26 -> 0
D35: =SUM(D29:D34) -> 1000

Sheet Evidência Conservador
B2: EVIDÊNCIA — PERFIL CONSERVADOR
B4: CONFIGURAÇÕES
B5: Salário | D5: 15000
B6: Rendimento Carteira | D6: 0.006
B7: Sugestão de Investimento (30%) | D7: =D5*30% -> 4500
B9: INVESTIMENTO MENSAL
B10: Quanto investir por mês ? | D10: 1000
B11: Por Quantos Anos ? | D11: 10
B12: Taxa de Rendimento mensal ? | D12: 0.01079
B13: Patrimônio acumulado ? | D13: =FV(taxa_mensal,qtd_anos*12,aporte*-1) -> 243284.21
B14: Dividendos Mensais ? | D14: =patrimonio*rendimento_carteira -> 1459.7053
B16: Cenários | D16: Dividendo
A17: 2 | B17: Quanto em 2 Anos ? | C17: =FV($D$12,$A17*12,$D$10*-1) -> 27227.627 | D17: =C17*rendimento_carteira -> 163.36576
A18: 5 | B18: Quanto em 5 Anos ? | C18: =FV($D$12,$A18*12,$D$10*-1) -> 83776.914 | D18: =C18*rendimento_carteira -> 502.66148
A19: 10 | B19: Quanto em 10 Anos ? | C19: =FV($D$12,$A19*12,$D$10*-1) -> 243284.21 | D19: =C19*rendimento_carteira -> 1459.7053
A20: 20 | B20: Quanto em 20 Anos ? | C20: =FV($D$12,$A20*12,$D$10*-1) -> 1125198.4 | D20: =C20*rendimento_carteira -> 6751.1904
A21: 30 | B21: Quanto em 30 Anos ? | C21: =FV($D$12,$A21*12,$D$10*-1) -> 4322169.7 | D21: =C21*rendimento_carteira -> 25933.018
B25: PERFIL | C25: Conservador
B26: VALOR A SER INVESTIDO POR MÊS | C26: =aporte -> 1000
B28: TIPO DE FII | C28: Percentual Sugerido | D28: Valores
B29: PAPEL | C29: =VLOOKUP($C$25&"-"&B29,Sheet2!$A:$D,4,FALSE) -> 0.3 | D29: =C29*$C$26 -> 300
B30: TIJOLO | C30: =VLOOKUP($C$25&"-"&B30,Sheet2!$A:$D,4,FALSE) -> 0.5 | D30: =C30*$C$26 -> 500
B31: HÍBRIDOS | C31: =VLOOKUP($C$25&"-"&B31,Sheet2!$A:$D,4,FALSE) -> 0.1 | D31: =C31*$C$26 -> 100
B32: FOFs | C32: =VLOOKUP($C$25&"-"&B32,Sheet2!$A:$D,4,FALSE) -> 0.1 | D32: =C32*$C$26 -> 100
B33: DESENVOLVIMENTO | C33: =VLOOKUP($C$25&"-"&B33,Sheet2!$A:$D,4,FALSE) -> 0 | D33: =C33*$C$26 -> 0
B34: HOTELARIAS | C34: =VLOOKUP($C$25&"-"&B34,Sheet2!$A:$D,4,FALSE) -> 0 | D34: =C34*$C$26 -> 0
D35: =SUM(D29:D34) -> 1000

Sheet Evidência Agressivo
B2: EVIDÊNCIA — PERFIL AGRESSIVO
B4: CONFIGURAÇÕES
B5: Salário | D5: 15000
B6: Rendimento Carteira | D6: 0.006
B7: Sugestão de Investimento (30%) | D7: =D5*30% -> 4500
B9: INVESTIMENTO MENSAL
B10: Quanto investir por mês ? | D10: 1000
B11: Por Quantos Anos ? | D11: 10
B12: Taxa de Rendimento mensal ? | D12: 0.01079
B13: Patrimônio acumulado ? | D13: =FV(taxa_mensal,qtd_anos*12,aporte*-1) -> 243284.21
B14: Dividendos Mensais ? | D14: =patrimonio*rendimento_carteira -> 1459.7053
B16: Cenários | D16: Dividendo
A17: 2 | B17: Quanto em 2 Anos ? | C17: =FV($D$12,$A17*12,$D$10*-1) -> 27227.627 | D17: =C17*rendimento_carteira -> 163.36576
A18: 5 | B18: Quanto em 5 Anos ? | C18: =FV($D$12,$A18*12,$D$10*-1) -> 83776.914 | D18: =C18*rendimento_carteira -> 502.66148
A19: 10 | B19: Quanto em 10 Anos ? | C19: =FV($D$12,$A19*12,$D$10*-1) -> 243284.21 | D19: =C19*rendimento_carteira -> 1459.7053
A20: 20 | B20: Quanto em 20 Anos ? | C20: =FV($D$12,$A20*12,$D$10*-1) -> 1125198.4 | D20: =C20*rendimento_carteira -> 6751.1904
A21: 30 | B21: Quanto em 30 Anos ? | C21: =FV($D$12,$A21*12,$D$10*-1) -> 4322169.7 | D21: =C21*rendimento_carteira -> 25933.018
B25: PERFIL | C25: Agressivo
B26: VALOR A SER INVESTIDO POR MÊS | C26: =aporte -> 1000
B28: TIPO DE FII | C28: Percentual Sugerido | D28: Valores
B29: PAPEL | C29: =VLOOKUP($C$25&"-"&B29,Sheet2!$A:$D,4,FALSE) -> 0.5 | D29: =C29*$C$26 -> 500
B30: TIJOLO | C30: =VLOOKUP($C$25&"-"&B30,Sheet2!$A:$D,4,FALSE) -> 0.1 | D30: =C30*$C$26 -> 100
B31: HÍBRIDOS | C31: =VLOOKUP($C$25&"-"&B31,Sheet2!$A:$D,4,FALSE) -> 0.05 | D31: =C31*$C$26 -> 50
B32: FOFs | C32: =VLOOKUP($C$25&"-"&B32,Sheet2!$A:$D,4,FALSE) -> 0.05 | D32: =C32*$C$26 -> 50
B33: DESENVOLVIMENTO | C33: =VLOOKUP($C$25&"-"&B33,Sheet2!$A:$D,4,FALSE) -> 0.2 | D33: =C33*$C$26 -> 200
B34: HOTELARIAS | C34: =VLOOKUP($C$25&"-"&B34,Sheet2!$A:$D,4,FALSE) -> 0.1 | D34: =C34*$C$26 -> 100
D35: =SUM(D29:D34) -> 1000

Sheet Sheet2
A2: CHAVE | B2: PERFIL | C2: TIPO DE FII | D2: %
A3: =B3&"-"&C3 -> Conservador-PAPEL | B3: Conservador | C3: PAPEL | D3: 0.3 | H3: %
A4: =B4&"-"&C4 -> Conservador-TIJOLO | B4: Conservador | C4: TIJOLO | D4: 0.5 | G4: =A4 -> Conservador-TIJOLO | H4: =VLOOKUP(G4,$A:$D,4,FALSE) -> 0.5
A5: =B5&"-"&C5 -> Conservador-HÍBRIDOS | B5: Conservador | C5: HÍBRIDOS | D5: 0.1
A6: =B6&"-"&C6 -> Conservador-FOFs | B6: Conservador | C6: FOFs | D6: 0.1
A7: =B7&"-"&C7 -> Conservador-DESENVOLVIMENTO | B7: Conservador | C7: DESENVOLVIMENTO | D7: 0
A8: =B8&"-"&C8 -> Conservador-HOTELARIAS | B8: Conservador | C8: HOTELARIAS | D8: 0
A9: =B9&"-"&C9 -> Moderado-PAPEL | B9: Moderado | C9: PAPEL | D9: 0.32
A10: =B10&"-"&C10 -> Moderado-TIJOLO | B10: Moderado | C10: TIJOLO | D10: 0.35
A11: =B11&"-"&C11 -> Moderado-HÍBRIDOS | B11: Moderado | C11: HÍBRIDOS | D11: 0.08
A12: =B12&"-"&C12 -> Moderado-FOFs | B12: Moderado | C12: FOFs | D12: 0.05
A13: =B13&"-"&C13 -> Moderado-DESENVOLVIMENTO | B13: Moderado | C13: DESENVOLVIMENTO | D13: 0.1
A14: =B14&"-"&C14 -> Moderado-HOTELARIAS | B14: Moderado | C14: HOTELARIAS | D14: 0.1
A15: =B15&"-"&C15 -> Agressivo-PAPEL | B15: Agressivo | C15: PAPEL | D15: 0.5
A16: =B16&"-"&C16 -> Agressivo-TIJOLO | B16: Agressivo | C16: TIJOLO | D16: 0.1
... A20: =B20&"-"&C20 -> Agressivo-HOTELARIAS | B20: Agressivo | C20: HOTELARIAS | D20: 0.1

Sheet Guia do Portfólio
A1: GUIA DA FERRAMENTA DE INVESTIMENTOS
A2: O que a ferramenta responde | B2: Entrada / lógica | C2: Onde aparece | D2: Resultado na simulação
A3: Quanto investir por mês? | B3: Aporte informado | C3: APP!D10 | D3: R$ 1.000,00
A4: Por quantos anos investir? | B4: Prazo informado | C4: APP!D11 | D4: 10 anos
A5: Qual o patrimônio acumulado? | B5: VF(taxa; meses; -aporte) | C5: APP!D13 | D5: R$ 243.284,21
A6: Qual a renda mensal estimada? | B6: Patrimônio × rendimento da carteira | C6: APP!D14 | D6: R$ 1.459,71
A7: Quanto acumula em 2, 5, 10, 20 e 30 anos? | B7: VF em cada prazo | C7: APP!C17:D21 | D7: Cenários e dividendos
A8: Como dividir o aporte entre FIIs? | B8: PROCV por perfil + tipo | C8: APP!C29:D34 | D8: Percentuais e valores
A10: INTERVALOS NOMEADOS | B10: Referência | C10: Uso
A11: aporte | B11: APP!$D$10 | C11: Pagamento mensal no VF e base da alocação
A12: qtd_anos | B12: APP!$D$11 | C12: Prazo × 12 meses no VF
A13: taxa_mensal | B13: APP!$D$12 | C13: Taxa periódica do VF
A14: patrimonio | B14: APP!$D$13 | C14: Base para calcular dividendos
A15: rendimento_carteira | B15: APP!$D$6 | C15: Percentual mensal aplicado ao patrimônio
A17: PERCENTUAIS POR PERFIL | B17: Papel | C17: Tijolo | D17: Híbridos / FOFs / Desenvolvimento / Hotelarias
A18: Conservador | B18: 0.3 | C18: 0.5 | D18: 10% / 10% / 0% / 0%
A19: Moderado | B19: 0.32 | C19: 0.35 | D19: 8% / 5% / 10% / 10%
A20: Agressivo | B20: 0.5 | C20: 0.1 | D20: 5% / 5% / 20% / 10%
A22: EVIDÊNCIA COMPARÁVEL | B22: Mesmo aporte | C22: Mesmo prazo e taxa | D22: Apenas o perfil muda
A23: Conservador | B23: R$ 1.000,00 | C23: 10 anos; 1,079% a.m. | D23: R$ 300 / 500 / 100 / 100 / 0 / 0
A24: Agressivo | B24: R$ 1.000,00 | C24: 10 anos; 1,079% a.m. | D24: R$ 500 / 100 / 50 / 50 / 200 / 100
A26: PRINCIPAIS ADAPTAÇÕES | B26: Seletor de perfil | C26: Base de percentuais + PROCV | D26: Cenários, dividendos e gráfico de alocação
A27: ORIGEM DOS PERCENTUAIS | B27: Premissas fixas cadastradas em Sheet2!B3:D20 | C27: Cada perfil soma 100% | D27: A planilha não contém fonte externa ou justificativa metodológica
A28: LEITURA DA COMPARAÇÃO | B28: O patrimônio não muda ao trocar o perfil | C28: O perfil altera somente a divisão do mesmo aporte | D28: Use as duas abas de evidência nos prints
A29: CORREÇÃO DE CONSISTÊNCIA | B29: A sugestão rotulada como 30% calculava 20% | C29: Fórmula ajustada para salário × 30% | D29: R$ 4.500,00 sobre salário de R$ 15.000,00
